LICENSE
README.md
setup.py
morchest/__init__.py
morchest.egg-info/PKG-INFO
morchest.egg-info/SOURCES.txt
morchest.egg-info/dependency_links.txt
morchest.egg-info/requires.txt
morchest.egg-info/top_level.txt