Metadata-Version: 2.1
Name: morchest
Version: 0.0.20
Summary: My short description for my project.
Home-page: https://github.com/franceme/morchest
Author: Miles Frantz
Author-email: frantzme@vt.edu
License: UNKNOWN
Platform: UNKNOWN
Classifier: Programming Language :: Python
Classifier: Programming Language :: Python :: 3
Classifier: Programming Language :: Python :: 3.8
Requires-Python: >=3.8.0
License-File: LICENSE
